README.md
package_info.json
setup.py
th2_grpc_common/__init__.py
th2_grpc_common/common.proto
th2_grpc_common/common_pb2.py
th2_grpc_common/common_pb2_grpc.py
th2_grpc_common.egg-info/PKG-INFO
th2_grpc_common.egg-info/SOURCES.txt
th2_grpc_common.egg-info/dependency_links.txt
th2_grpc_common.egg-info/requires.txt
th2_grpc_common.egg-info/top_level.txt